.coveragerc
.travis.yml
README.rst
bootstrap.py
buildout.cfg
rebuild_i18n.sh
setup.py
test-4.0.x.cfg
test-4.1.x.cfg
test-4.2.x.cfg
test-4.3.x.cfg
collective/__init__.py
collective.embedly.egg-info/PKG-INFO
collective.embedly.egg-info/SOURCES.txt
collective.embedly.egg-info/dependency_links.txt
collective.embedly.egg-info/entry_points.txt
collective.embedly.egg-info/namespace_packages.txt
collective.embedly.egg-info/not-zip-safe
collective.embedly.egg-info/requires.txt
collective.embedly.egg-info/top_level.txt
collective/embedly/README.txt
collective/embedly/__init__.py
collective/embedly/configure.zcml
collective/embedly/interfaces.py
collective/embedly/setuphandlers.py
collective/embedly/transform.py
collective/embedly/Extensions/Install.py
collective/embedly/browser/__init__.py
collective/embedly/browser/configure.zcml
collective/embedly/browser/controlpanel.py
collective/embedly/browser/embedly.css
collective/embedly/browser/embedly.png
collective/embedly/browser/tools.py
collective/embedly/browser/plugin/editor_plugin.js
collective/embedly/browser/plugin/embedly.pt
collective/embedly/browser/plugin/css/embedlylink.css
collective/embedly/browser/plugin/js/embedlylink.dev.js
collective/embedly/browser/plugin/js/embedlylink.js
collective/embedly/locales/collective.embedly.pot
collective/embedly/locales/manual.pot
collective/embedly/locales/de/LC_MESSAGES/collective.embedly.po
collective/embedly/locales/pt_BR/LC_MESSAGES/collective.embedly.po
collective/embedly/profiles/default/collective.embedly.install.txt
collective/embedly/profiles/default/controlpanel.xml
collective/embedly/profiles/default/cssregistry.xml
collective/embedly/profiles/default/metadata.xml
collective/embedly/profiles/default/registry.xml
collective/embedly/profiles/uninstall/collective.embedly.uninstall.txt
collective/embedly/profiles/uninstall/registry.xml
collective/embedly/tests/__init__.py
collective/embedly/tests/layer.py
collective/embedly/tests/patch.py
collective/embedly/tests/test_controlpanel.py
collective/embedly/tests/test_embedly.txt
collective/embedly/tests/tests.py
docs/HISTORY.rst
docs/INSTALL.txt
docs/LICENSE.GPL
docs/LICENSE.txt