Metadata-Version: 1.0
Name: collective.embedly
Version: 2.4
Summary: TinyMCE visual editor support for embed.ly service
Home-page: https://github.com/collective/collective.embedly
Author: Quintagroup
Author-email: support@quintagroup.com
License: GPL
Keywords: web zope plone embedly TinyMCE plugin multimedia
Platform: UNKNOWN
Classifier: Framework :: Plone
Classifier: Framework :: Plone :: 4.1
Classifier: Framework :: Plone :: 4.2
Classifier: Framework :: Plone :: 4.3
Classifier: Programming Language :: Python
Classifier: Development Status :: 5 - Production/Stable
Classifier: Environment :: Plugins
Classifier: Intended Audience :: Developers
Classifier: Natural Language :: English
Classifier: Operating System :: OS Independent
Classifier: Programming Language :: Python
Classifier: Topic :: Internet :: WWW/HTTP :: Dynamic Content
Classifier: Topic :: Multimedia
Classifier: Topic :: Multimedia :: Graphics
Classifier: Topic :: Multimedia :: Sound/Audio
Classifier: Topic :: Multimedia :: Video
Classifier: Topic :: Software Development :: Libraries :: Python Modules
Classifier: License :: OSI Approved :: GNU General Public License (GPL)
